flask_socketio_web/__init__.py
flask_socketio_web/action.py
flask_socketio_web/sio.py
flask_socketio_web/sio_server.py
flask_socketio_web/common/response.py
flask_socketio_web/common/token_util.py
flask_socketio_web/common/util.py
flask_socketio_web-0.0.4.dist-info/LICENSE
flask_socketio_web-0.0.4.dist-info/METADATA
flask_socketio_web-0.0.4.dist-info/WHEEL
flask_socketio_web-0.0.4.dist-info/top_level.txt
flask_socketio_web-0.0.4.dist-info/RECORD
