Metadata-Version: 2.1
Name: flask-socketio-web
Version: 0.0.4
Summary: flask-socketio-web
Author: hammer
Author-email: liuzhuogood@foxmail.com
License: UNKNOWN
Platform: UNKNOWN
License-File: LICENSE
Requires-Dist: python-socketio
Requires-Dist: flask
Requires-Dist: python-engineio
Requires-Dist: loguru
